<?xml version="1.0" encoding="UTF-8" standalone="yes"?>



<channels>
<channel>
<name>[COLOR red]J[/COLOR][COLOR blue]H[/COLOR][COLOR red]G[/COLOR] [COLOR yellow] Temporada 1[/COLOR] </name>
<thumbnail></thumbnail>
<fanart></fanart>
<items>




<item>
<title>[COLOR red]J[/COLOR][COLOR blue]H[/COLOR][COLOR red]G[/COLOR] 1x01 La Suerte</title>
<urlsolve>http://streamcloud.eu/bj2tvi7vn6jc/Los_Hombres_de_Paco_1x01.avi.html</urlsolve>
<thumbnail></thumbnail>
<fanart></fanart>
</item>




<item>
<title>[COLOR red]J[/COLOR][COLOR blue]H[/COLOR][COLOR red]G[/COLOR] 1x02 La paranoia </title>
<urlsolve>http://streamcloud.eu/08hys34boit3/Los_Hombres_de_Paco_1x02.avi.html</urlsolve>
<thumbnail></thumbnail>
<fanart></fanart>
</item>




<item>
<title>[COLOR red]J[/COLOR][COLOR blue]H[/COLOR][COLOR red]G[/COLOR] 1x03 La mentira</title>
<urlsolve>http://streamcloud.eu/qq2fi1sdnq3k/Los_hombres_de_paco_1x03.avi.html</urlsolve>
<thumbnail></thumbnail>
<fanart></fanart>
</item>



<item>
<title>[COLOR red]J[/COLOR][COLOR blue]H[/COLOR][COLOR red]G[/COLOR] 1x04 Operación Picachu</title>
<urlsolve>http://streamcloud.eu/2iz8lzw4reo7/Los_Hombres_de_Paco_1x04.avi.html</urlsolve>
<thumbnail></thumbnail>
<fanart></fanart>
</item>




<item>
<title>[COLOR red]J[/COLOR][COLOR blue]H[/COLOR][COLOR red]G[/COLOR] 1x05 El instinto </title>
<urlsolve>http://streamcloud.eu/pntxjpaeorin/Los_hombres_de_paco_1x05.avi.html</urlsolve>
<thumbnail></thumbnail>
<fanart></fanart>
</item>




<item>
<title>[COLOR red]J[/COLOR][COLOR blue]H[/COLOR][COLOR red]G[/COLOR] 1x06 El apocalipsis</title>
<urlsolve>http://streamcloud.eu/qqntpkfivcpj/Los_hombres_de_paco_1x06.avi.html</urlsolve>
<thumbnail></thumbnail>
<fanart></fanart>
</item>




<item>
<title>[COLOR red]J[/COLOR][COLOR blue]H[/COLOR][COLOR red]G[/COLOR] 1x07 El brillo del oropel</title>
<urlsolve>http://streamcloud.eu/xa4hyb6o1fhk/Los_hombres_de_paco_1x07.avi.html</urlsolve>
<thumbnail></thumbnail>
<fanart></fanart>
</item>




<item>
<title>[COLOR red]J[/COLOR][COLOR blue]H[/COLOR][COLOR red]G[/COLOR] 1x08 Un lugar en el mundo</title>
<urlsolve>http://streamcloud.eu/ko7p1brpa10j/Los_hombres_de_paco_1x08.avi.html</urlsolve>
<thumbnail></thumbnail>
<fanart></fanart>
</item>




<item>
<title>[COLOR red]J[/COLOR][COLOR blue]H[/COLOR][COLOR red]G[/COLOR] 1x09 El silencio de los maderos</title>
<urlsolve>http://streamcloud.eu/h1y6ppei1umb/Los_hombres_de_paco_1x09.avi.html</urlsolve>
<thumbnail></thumbnail>
<fanart></fanart>
</item>




<item>
<title>[COLOR red]J[/COLOR][COLOR blue]H[/COLOR][COLOR red]G[/COLOR] 1x10 La mafia calabresa</title>
<urlsolve>http://streamcloud.eu/eiz86uer01r9/Los_hombres_de_paco_1x10.avi.html</urlsolve>
<thumbnail></thumbnail>
<fanart></fanart>
</item>




<item>
<title>[COLOR red]J[/COLOR][COLOR blue]H[/COLOR][COLOR red]G[/COLOR]  1x11 Con faja y a lo loco</title>
<urlsolve>http://streamcloud.eu/09skf6ln0c1x/Los_hombres_de_paco_1x11.avi.html</urlsolve>
<thumbnail></thumbnail>
<fanart></fanart>
</item>




<item>
<title>[COLOR red]J[/COLOR][COLOR blue]H[/COLOR][COLOR red]G[/COLOR] 1x12 Vade retro, Satanás</title>
<urlsolve>http://streamcloud.eu/pv619pa7440r/Los_hombres_de_paco_1x12.avi.html</urlsolve>
<thumbnail></thumbnail>
<fanart></fanart>
</item>



<item>
<title>[COLOR red]J[/COLOR][COLOR blue]H[/COLOR][COLOR red]G[/COLOR] 1x13 Una de romanos</title>
<urlsolve>http://streamcloud.eu/yz4kxvg4binx/Los_hombres_de_paco_1x13.avi.html</urlsolve>
<thumbnail></thumbnail>
<fanart></fanart>
</item>
</items>
</channel>



<channel>
<name>[COLOR red]J[/COLOR][COLOR blue]H[/COLOR][COLOR red]G [/COLOR] [COLOR yellow] Temporada 2[/COLOR] </name>
<thumbnail></thumbnail>
<fanart></fanart>
<items>



<item>
<title>[COLOR red]J[/COLOR][COLOR blue]H[/COLOR][COLOR red]G[/COLOR] 2x01 Amigos hasta la muerte</title>
<urlsolve>http://streamcloud.eu/pm2sztkb44cc/Los_Hombres_de_Paco_2x01.avi.html</urlsolve>
<thumbnail></thumbnail>
<fanart></fanart>
</item>



<item>
<title>[COLOR red]J[/COLOR][COLOR blue]H[/COLOR][COLOR red]G[/COLOR] 2x02 Con escarcha en el pelo</title>
<urlsolve>http://www.nowvideo.sx/video/3894ae941df64</urlsolve>
<thumbnail></thumbnail>
<fanart></fanart>
</item>




<item>
<title>[COLOR red]J[/COLOR][COLOR blue]H[/COLOR][COLOR red]G[/COLOR] 2x03 Tigre y dragón</title>
<urlsolve>http://streamcloud.eu/i4blw2t61qsx/Los_hombres_de_paco_2x03.avi.html</urlsolve>
<thumbnail></thumbnail>
<fanart></fanart>
</item>




<item>
<title>[COLOR red]J[/COLOR][COLOR blue]H[/COLOR][COLOR red]G[/COLOR] 2x04 Rollito de primavera</title>
<urlsolve>http://streamcloud.eu/me4f6f1p0y5c/Los_Hombres_de_Paco_2x04.avi.html</urlsolve>
<thumbnail></thumbnail>
<fanart></fanart>
</item>




<item>
<title>[COLOR red]J[/COLOR][COLOR blue]H[/COLOR][COLOR red]G[/COLOR] 2x05 Aterriza con las muelas</title>
<urlsolve>http://streamcloud.eu/1nk0u09wgf3l/Los_hombres_de_paco_2x05.avi.html</urlsolve>
<thumbnail></thumbnail>
<fanart></fanart>
</item>





<item>
<title>[COLOR red]J[/COLOR][COLOR blue]H[/COLOR][COLOR red]G[/COLOR] 2x06 Todo el mundo al suelo</title>
<urlsolve>http://streamcloud.eu/z704hhlqy0at/Los_Hombres_de_Paco_2x06.avi.html</urlsolve>
<thumbnail></thumbnail>
<fanart></fanart>
</item>


<item>
<title>[COLOR red]J[/COLOR][COLOR blue]H[/COLOR][COLOR red]G[/COLOR] 2x07 La famiglia</title>
<urlsolve>http://streamcloud.eu/deydgqf4ifga/Los_hombres_de_paco_2x07.avi.html</urlsolve>
<thumbnail></thumbnail>
<fanart></fanart>
</item>


<item>
<title>[COLOR red]J[/COLOR][COLOR blue]H[/COLOR][COLOR red]G[/COLOR] 2x08 Sin tregua</title>
<urlsolve>http://streamcloud.eu/qrwyfj47r62q/Los_Hombres_de_Paco_2x08.avi.html</urlsolve>
<thumbnail></thumbnail>
<fanart></fanart>
</item>





<item>
<title>[COLOR red]J[/COLOR][COLOR blue]H[/COLOR][COLOR red]G[/COLOR] 2x09 Pleno al quince</title>
<urlsolve>http://streamcloud.eu/inzxkqpa8kdk/Los_Hombres_de_Paco_2x09.avi.html</urlsolve>
<thumbnail></thumbnail>
<fanart></fanart>
</item>


<item>
<title>[COLOR red]J[/COLOR][COLOR blue]H[/COLOR][COLOR red]G[/COLOR] 2x10 Los hombres de Osama</title>
<urlsolve>http://streamcloud.eu/dfi9gn2krvrg/Los_Hombres_de_Paco_2x10.mkv.html</urlsolve>
<thumbnail></thumbnail>
<fanart></fanart>
</item>


<item>
<title>[COLOR red]J[/COLOR][COLOR blue]H[/COLOR][COLOR red]G[/COLOR] 2x11 De la fosa al pilón</title>
<urlsolve>http://streamcloud.eu/xyrgp8lvox8h/Los_Hombres_de_Paco_2x11.avi.html</urlsolve>
<thumbnail></thumbnail>
<fanart></fanart>
</item>




<item>
<title>[COLOR red]J[/COLOR][COLOR blue]H[/COLOR][COLOR red]G[/COLOR] 2x12 Tarde de toros</title>
<urlsolve>http://streamcloud.eu/gi6engwkfjw1/Los_Hombres_de_Paco_2x12.avi.html</urlsolve>
<thumbnail></thumbnail>
<fanart></fanart>
</item>


<item>
<title>[COLOR red]J[/COLOR][COLOR blue]H[/COLOR][COLOR red]G[/COLOR] 2x13 El código Vicente</title>
<urlsolve>http://streamcloud.eu/m5w01hqih5dl/Los_hombres_de_paco_2x13.avi.html</urlsolve>
<thumbnail></thumbnail>
<fanart></fanart>
</item>


<item>
<title>[COLOR red]J[/COLOR][COLOR blue]H[/COLOR][COLOR red]G[/COLOR] 2x14 Bajo tierra</title>
<urlsolve>http://streamcloud.eu/bacy0igaswri/Los_hombres_de_paco_2x14.avi.html</urlsolve>
<thumbnail></thumbnail>
<fanart></fanart>
</item>
</items>
</channel>



<channel>
<name>[COLOR red]J[/COLOR][COLOR blue]H[/COLOR][COLOR red]G [/COLOR] [COLOR yellow] Temporada 3[/COLOR] </name>
<thumbnail></thumbnail>
<fanart></fanart>
<items>



<item>
<title>[COLOR red]J[/COLOR][COLOR blue]H[/COLOR][COLOR red]G[/COLOR] 3x01 Vértigo</title>
<urlsolve>http://streamcloud.eu/gkjr3rt5b0mi/Los_hombres_de_paco_3x01.avi.html</urlsolve>
<thumbnail></thumbnail>
<fanart></fanart>
</item>


<item>
<title>[COLOR red]J[/COLOR][COLOR blue]H[/COLOR][COLOR red]G[/COLOR] 3x02 Ración de oreja</title>
<urlsolve>http://streamcloud.eu/1kr3ns1hygr4/Los_hombres_de_paco_3x02.avi.html</urlsolve>
<thumbnail></thumbnail>
<fanart></fanart>
</item>


<item>
<title>[COLOR red]J[/COLOR][COLOR blue]H[/COLOR][COLOR red]G[/COLOR] 3x03 Todo tiene arreglo</title>
<urlsolve>http://streamcloud.eu/mzy7zg0jl6a5/Los_hombres_de_paco_3x03.avi.html</urlsolve>
<thumbnail></thumbnail>
<fanart></fanart>
</item>



<item>
<title>[COLOR red]J[/COLOR][COLOR blue]H[/COLOR][COLOR red]G[/COLOR] 3x04 El madero biónico</title>
<urlsolve>http://streamcloud.eu/qqx0uu55lpas/Los_hombres_de_paco_3x04.flv.html</urlsolve>
<thumbnail></thumbnail>
<fanart></fanart>
</item>




<item>
<title>[COLOR red]J[/COLOR][COLOR blue]H[/COLOR][COLOR red]G[/COLOR] 3x05 Cariño y metadona</title>
<urlsolve>http://streamcloud.eu/3geqfoq0m7es/Los_hombres_de_paco_3x05.avi.html</urlsolve>
<thumbnail></thumbnail>
<fanart></fanart>
</item>




<item>
<title>[COLOR red]J[/COLOR][COLOR blue]H[/COLOR][COLOR red]G[/COLOR] 3x06 Un día tonto lo tiene cualquiera</title>
<urlsolve>http://streamcloud.eu/d9u8ffpksz3m/Los_hombres_de_paco_3x06.avi.html</urlsolve>
<thumbnail></thumbnail>
<fanart></fanart>
</item>



<item>
<title>[COLOR red]J[/COLOR][COLOR blue]H[/COLOR][COLOR red]G[/COLOR] 3x07 ¿En qué día mi vida se convirtió en un sueño?</title>
<urlsolve>http://streamcloud.eu/1eueyvi07ol6/Los_hombres_de_paco_3x07.avi.html</urlsolve>
<thumbnail></thumbnail>
<fanart></fanart>
</item>



<item>
<title>[COLOR red]J[/COLOR][COLOR blue]H[/COLOR][COLOR red]G[/COLOR] 3x08 Expediente Berni</title>
<urlsolve>http://streamcloud.eu/hdbe55p1svvu/Los_hombres_de_paco_3x08.avi.html</urlsolve>
<thumbnail></thumbnail>
<fanart></fanart>
</item>





<item>
<title>[COLOR red]J[/COLOR][COLOR blue]H[/COLOR][COLOR red]G[/COLOR] 3x09 Cuando Rita encontró a Pove</title>
<urlsolve>http://streamcloud.eu/2rp6r7186fag/Los_hombres_de_paco_3x09.avi.html</urlsolve>
<thumbnail></thumbnail>
<fanart></fanart>
</item>




<item>
<title>[COLOR red]J[/COLOR][COLOR blue]H[/COLOR][COLOR red]G[/COLOR] 3x10 El chorro polar</title>
<urlsolve>http://streamcloud.eu/ls0kovhuaz5l/Los_hombres_de_paco_3x10.avi.html</urlsolve>
<thumbnail></thumbnail>
<fanart></fanart>
</item>





<item>
<title>[COLOR red]J[/COLOR][COLOR blue]H[/COLOR][COLOR red]G[/COLOR] 3x11 El tío Walt</title>
<urlsolve>http://streamcloud.eu/7dplkr01wcyu/Los_hombres_de_paco_3x11.avi.html</urlsolve>
<thumbnail></thumbnail>
<fanart></fanart>
</item>




<item>
<title>[COLOR red]J[/COLOR][COLOR blue]H[/COLOR][COLOR red]G[/COLOR] 3x12 El yalovi</title>
<urlsolve>http://streamcloud.eu/jdfcx93vi9ni/Los_hombres_de_paco_3x12.avi.html</urlsolve>
<thumbnail></thumbnail>
<fanart></fanart>
</item>






<item>
<title>[COLOR red]J[/COLOR][COLOR blue]H[/COLOR][COLOR red]G[/COLOR] 3x13 Padre no hay más que uno</title>
<urlsolve>http://streamcloud.eu/9274z437aynx/Los_hombres_de_paco_3x13.avi.html</urlsolve>
<thumbnail></thumbnail>
<fanart></fanart>
</item>
</items>
</channel>



<channel>
<name>[COLOR red]J[/COLOR][COLOR blue]H[/COLOR][COLOR red]G[/COLOR] [COLOR yellow] Temporada 4[/COLOR] </name>
<thumbnail></thumbnail>
<fanart></fanart>
<items>



<item>
<title>[COLOR red]J[/COLOR][COLOR blue]H[/COLOR][COLOR red]G[/COLOR] 4x01 Todo sobre mi padre</title>
<urlsolve>http://streamcloud.eu/51kvut5z151w/Los_hombres_de_paco_4x01.avi.html</urlsolve>
<thumbnail></thumbnail>
<fanart></fanart>
</item>



<item>
<title>[COLOR red]J[/COLOR][COLOR blue]H[/COLOR][COLOR red]G[/COLOR] </title>
<urlsolve></urlsolve>
<thumbnail></thumbnail>
<fanart></fanart>
</item>



<item>
<title>[COLOR red]J[/COLOR][COLOR blue]H[/COLOR][COLOR red]G[/COLOR] </title>
<urlsolve></urlsolve>
<thumbnail></thumbnail>
<fanart></fanart>
</item>




<item>
<title>[COLOR red]J[/COLOR][COLOR blue]H[/COLOR][COLOR red]G[/COLOR] </title>
<urlsolve></urlsolve>
<thumbnail></thumbnail>
<fanart></fanart>
</item>



<item>
<title>[COLOR red]J[/COLOR][COLOR blue]H[/COLOR][COLOR red]G[/COLOR] </title>
<urlsolve></urlsolve>
<thumbnail></thumbnail>
<fanart></fanart>
</item>



<item>
<title>[COLOR red]J[/COLOR][COLOR blue]H[/COLOR][COLOR red]G[/COLOR] </title>
<urlsolve></urlsolve>
<thumbnail></thumbnail>
<fanart></fanart>
</item>




<item>
<title>[COLOR red]J[/COLOR][COLOR blue]H[/COLOR][COLOR red]G[/COLOR] </title>
<urlsolve></urlsolve>
<thumbnail></thumbnail>
<fanart></fanart>
</item>




<item>
<title>[COLOR red]J[/COLOR][COLOR blue]H[/COLOR][COLOR red]G[/COLOR] </title>
<urlsolve></urlsolve>
<thumbnail></thumbnail>
<fanart></fanart>
</item>



<item>
<title>[COLOR red]J[/COLOR][COLOR blue]H[/COLOR][COLOR red]G[/COLOR] </title>
<urlsolve></urlsolve>
<thumbnail></thumbnail>
<fanart></fanart>
</item>




<item>
<title>[COLOR red]J[/COLOR][COLOR blue]H[/COLOR][COLOR red]G[/COLOR] </title>
<urlsolve></urlsolve>
<thumbnail></thumbnail>
<fanart></fanart>
</item>





<item>
<title>[COLOR red]J[/COLOR][COLOR blue]H[/COLOR][COLOR red]G[/COLOR] </title>
<urlsolve></urlsolve>
<thumbnail></thumbnail>
<fanart></fanart>
</item>



<item>
<title>[COLOR red]J[/COLOR][COLOR blue]H[/COLOR][COLOR red]G[/COLOR] </title>
<urlsolve></urlsolve>
<thumbnail></thumbnail>
<fanart></fanart>
</item>
</items>
</channel>
</channels>