<?xml version="1.0" encoding="UTF-8" standalone="yes"?>





<channels>
<channel>
<name>[COLOR red]J[/COLOR][COLOR blue]H[/COLOR][COLOR red]G[/COLOR] [COLOR yellow] Temporada 1[/COLOR] </name>
<thumbnail></thumbnail>
<fanart></fanart>
<items>



<item>
<title>[COLOR red]J[/COLOR][COLOR blue]H[/COLOR][COLOR red]G[/COLOR] 1x01 Episode 1</title>
<urlsolve>http://streamcloud.eu/9v43wg7t2rk4/P.L.1x01.es.avi.html</urlsolve>
<thumbnail></thumbnail>
<fanart></fanart>
</item>



<item>
<title>[COLOR red]J[/COLOR][COLOR blue]H[/COLOR][COLOR red]G[/COLOR] 1x02 Episode 2</title>
<urlsolve>http://streamcloud.eu/hkrgxozt4bbx/P.L.1x02.es.avi.html</urlsolve>
<thumbnail></thumbnail>
<fanart></fanart>
</item>



<item>
<title>[COLOR red]J[/COLOR][COLOR blue]H[/COLOR][COLOR red]G[/COLOR] 1x03 Episode 3</title>
<urlsolve>http://gamovideo.com/aavrgxxzwelm</urlsolve>
<thumbnail></thumbnail>
<fanart></fanart>
</item>



<item>
<title>[COLOR red]J[/COLOR][COLOR blue]H[/COLOR][COLOR red]G[/COLOR] 1x04 Episode 4</title>
<urlsolve>http://www.nowvideo.sx/video/0943233bb2ead</urlsolve>
<thumbnail></thumbnail>
<fanart></fanart>
</item>




<item>
<title>[COLOR red]J[/COLOR][COLOR blue]H[/COLOR][COLOR red]G[/COLOR] 1x05 Episode 5</title>
<urlsolve></urlsolve>
<thumbnail></thumbnail>
<fanart></fanart>
</item>



<item>
<title>[COLOR red]J[/COLOR][COLOR blue]H[/COLOR][COLOR red]G[/COLOR] </title>
<urlsolve></urlsolve>
<thumbnail></thumbnail>
<fanart></fanart>
</item>



<item>
<title>[COLOR red]J[/COLOR][COLOR blue]H[/COLOR][COLOR red]G[/COLOR] </title>
<urlsolve></urlsolve>
<thumbnail></thumbnail>
<fanart></fanart>
</item>





<item>
<title>[COLOR red]J[/COLOR][COLOR blue]H[/COLOR][COLOR red]G[/COLOR]  </title>
<urlsolve></urlsolve>
<thumbnail></thumbnail>
<fanart></fanart>
</item>
</items>
</channel>



<channel>
<name>[COLOR red]J[/COLOR][COLOR blue]H[/COLOR][COLOR red]G [/COLOR] [COLOR yellow] Temporada 2[/COLOR] </name>
<thumbnail></thumbnail>
<fanart></fanart>
<items>




<item>
<title>[COLOR red]J[/COLOR][COLOR blue]H[/COLOR][COLOR red]G[/COLOR] </title>
<urlsolve></urlsolve>
<thumbnail></thumbnail>
<fanart></fanart>
</item>





<item>
<title>[COLOR red]J[/COLOR][COLOR blue]H[/COLOR][COLOR red]G[/COLOR] </title>
<urlsolve></urlsolve>
<thumbnail></thumbnail>
<fanart></fanart>
</item>
</items>
</channel>
</channels>